bluesky_stomp/__init__.py
bluesky_stomp/__main__.py
bluesky_stomp/_version.py
bluesky_stomp/messaging.py
bluesky_stomp/models.py
bluesky_stomp/serdes.py
bluesky_stomp/utils.py
bluesky_stomp-0.2.0.dist-info/licenses/LICENSE
bluesky_stomp-0.2.0.dist-info/METADATA
bluesky_stomp-0.2.0.dist-info/WHEEL
bluesky_stomp-0.2.0.dist-info/entry_points.txt
bluesky_stomp-0.2.0.dist-info/top_level.txt
bluesky_stomp-0.2.0.dist-info/RECORD
