Metadata-Version: 2.4
Name: bluesky-stomp
Version: 0.2.0
Summary: STOMP integration for bluesky
Author-email: Callum Forrester <callum.forrester@diamond.ac.uk>
License:                                  Apache License
Project-URL: GitHub, https://github.com/DiamondLightSource/bluesky-stomp
Classifier: Development Status :: 3 - Alpha
Classifier: License :: OSI Approved :: Apache Software License
Classifier: Programming Language :: Python :: 3.10
Classifier: Programming Language :: Python :: 3.11
Classifier: Programming Language :: Python :: 3.12
Requires-Python: >=3.10
License-File: LICENSE
Requires-Dist: event-model
Requires-Dist: stomp-py
Requires-Dist: observability-utils
Requires-Dist: orjson
Requires-Dist: pydantic
Provides-Extra: dev
Requires-Dist: bluesky-stomp[demo]; extra == "dev"
Requires-Dist: copier; extra == "dev"
Requires-Dist: numpy; extra == "dev"
Requires-Dist: pipdeptree; extra == "dev"
Requires-Dist: pre-commit; extra == "dev"
Requires-Dist: pyright; extra == "dev"
Requires-Dist: pytest; extra == "dev"
Requires-Dist: pytest-cov; extra == "dev"
Requires-Dist: ruff; extra == "dev"
Requires-Dist: tox-direct; extra == "dev"
Requires-Dist: types-mock; extra == "dev"
Provides-Extra: demo
Requires-Dist: bluesky; extra == "demo"
Requires-Dist: ophyd-async; extra == "demo"
Requires-Dist: IPython; extra == "demo"
Requires-Dist: h5py; extra == "demo"
Requires-Dist: prompt_toolkit>=3.0.47; extra == "demo"
Requires-Dist: suitcase-csv; extra == "demo"
Dynamic: license-file
